pytinybeans/__init__.py
pytinybeans/pytinybeans.py
pytinybeans-1.1.dist-info/METADATA
pytinybeans-1.1.dist-info/WHEEL
pytinybeans-1.1.dist-info/top_level.txt
pytinybeans-1.1.dist-info/RECORD
