Metadata-Version: 2.1
Name: pytinybeans
Version: 1.1
Summary: Python library to interact with the Tinybeans API
Home-page: https://github.com/kjoconnor/pytinybeans
Author: Kevin O'Connor
Author-email: kjoconnor@gmail.com
License: UNKNOWN
Platform: UNKNOWN
Classifier: Programming Language :: Python :: 3
Classifier: License :: OSI Approved :: MIT License
Requires-Python: >=3.5
Requires-Dist: requests
